mcp_server_ladybug/__init__.py
mcp_server_ladybug/__main__.py
mcp_server_ladybug/configs.py
mcp_server_ladybug/database.py
mcp_server_ladybug/prompt.py
mcp_server_ladybug/server.py
mcp_server_ladybug-0.1.2.dist-info/METADATA
mcp_server_ladybug-0.1.2.dist-info/WHEEL
mcp_server_ladybug-0.1.2.dist-info/entry_points.txt
mcp_server_ladybug-0.1.2.dist-info/licenses/LICENSE
mcp_server_ladybug-0.1.2.dist-info/RECORD
