Metadata-Version: 2.4
Name: mcp-server-ladybug
Version: 0.1.2
Summary: A MCP server for LadybugDB - an embedded graph database with Cypher query language
License-File: LICENSE
Requires-Python: >=3.10
Requires-Dist: anyio>=4.8.0
Requires-Dist: click>=8.1.8
Requires-Dist: mcp>=1.9.4
Requires-Dist: real-ladybug>=0.14.0
Requires-Dist: starlette>=0.46.1
Requires-Dist: tabulate>=0.9.0
Requires-Dist: uvicorn>=0.34.0
